dshelper/__init__.py
dshelper/dshelper.py
dshelper/main_gui.py
dshelper/components/__init__.py
dshelper/components/log.py
dshelper/components/selection.py
dshelper/components/splash.py
dshelper/components/status_bar.py
dshelper/data/__init__.py
dshelper/data/data_panel.py
dshelper/data/utils.py
dshelper/datasets/__init__.py
dshelper/datasets/_titanic.py
dshelper/datasets/data/titanic.csv
dshelper/media/1.png
dshelper/media/2.png
dshelper/media/3.png
dshelper/media/4.png
dshelper/media/5.png
dshelper/media/6.png
dshelper/media/7.png
dshelper/media/8.png
dshelper/media/9.png
dshelper/media/forest.png
dshelper/media/splash.png
dshelper/plot/__init__.py
dshelper/plot/box_violin.py
dshelper/plot/heat.py
dshelper/plot/hist.py
dshelper/plot/pair.py
dshelper/plot/plot_panel.py
dshelper/plot/scatter.py
dshelper/plot/utils.py
dshelper/plots/__init__.py
dshelper/plots/box_violin.py
dshelper/plots/heat.py
dshelper/plots/hist.py
dshelper/plots/pair.py
dshelper/plots/plot_panel.py
dshelper/plots/scatter.py
dshelper/plots/utils.py
dshelper-0.2.0.dist-info/LICENSE
dshelper-0.2.0.dist-info/METADATA
dshelper-0.2.0.dist-info/WHEEL
dshelper-0.2.0.dist-info/top_level.txt
dshelper-0.2.0.dist-info/RECORD
